seafileapi/__init__.py
seafileapi/admin.py
seafileapi/client.py
seafileapi/exceptions.py
seafileapi/files.py
seafileapi/group.py
seafileapi/repo.py
seafileapi/repos.py
seafileapi/utils.py
seafileapi-0.1.1.dist-info/DESCRIPTION.rst
seafileapi-0.1.1.dist-info/METADATA
seafileapi-0.1.1.dist-info/metadata.json
seafileapi-0.1.1.dist-info/RECORD
seafileapi-0.1.1.dist-info/top_level.txt
seafileapi-0.1.1.dist-info/WHEEL
tests/__init__.py
tests/base.py
tests/test_files.py
tests/test_repo.py
tests/test_repos.py
tests/utils.py
