Metadata-Version: 2.0
Name: seafileapi
Version: 0.1.1
Summary: Client interface for Seafile Web API
Home-page: http://seafile.com
Author: Shuai Lin
Author-email: linshuai2012@gmail.com
License: BSD
Platform: Any
Classifier: Development Status :: 4 - Beta
Classifier: License :: OSI Approved :: BSD License
Classifier: Operating System :: OS Independent
Classifier: Programming Language :: Python
Requires-Dist: requests
